necstdb/__init__.py
necstdb/necstdb.py
necstdb/recover.py
necstdb/utils/__init__.py
necstdb/utils/data_utils.py
necstdb/utils/struct_utils.py
necstdb-0.2.9.dist-info/LICENSE
necstdb-0.2.9.dist-info/WHEEL
necstdb-0.2.9.dist-info/METADATA
necstdb-0.2.9.dist-info/RECORD
