Metadata-Version: 2.1
Name: necstdb
Version: 0.2.9
Summary: Database for NECST.
Home-page: https://github.com/ogawa-ros/necstdb
License: MIT
Author: Kaoru Nishikawa
Author-email: k.nishikawa@a.phys.nagoya-u.ac.jp
Requires-Python: >=3.6.1,<4.0.0
Classifier: License :: OSI Approved :: MIT License
Classifier: Operating System :: MacOS :: MacOS X
Classifier: Operating System :: POSIX :: Linux
Classifier: Programming Language :: Python
Classifier: Programming Language :: Python :: 3
Classifier: Programming Language :: Python :: 3.7
Classifier: Programming Language :: Python :: 3.8
Classifier: Programming Language :: Python :: 3.9
Classifier: Programming Language :: Python :: 3.10
Classifier: Programming Language :: Python :: 3.11
Classifier: Programming Language :: Python :: 3
Classifier: Topic :: Software Development :: Libraries :: Python Modules
Requires-Dist: numpy (>=1.19,<2.0)
Requires-Dist: pandas (>=1.1,<2.0)
Project-URL: Repository, https://github.com/ogawa-ros/necstdb
